ntsubtree/__init__.py
ntsubtree/constants.py
ntsubtree/ntsubtree.py
ntsubtree/commands/__init__.py
ntsubtree/commands/attribute.py
ntsubtree/commands/query.py
ntsubtree/commands/update.py
ntsubtree-1.1.data/scripts/ntsubtree
ntsubtree-1.1.dist-info/AUTHORS.txt
ntsubtree-1.1.dist-info/LICENSE.txt
ntsubtree-1.1.dist-info/METADATA
ntsubtree-1.1.dist-info/WHEEL
ntsubtree-1.1.dist-info/top_level.txt
ntsubtree-1.1.dist-info/RECORD
