Metadata-Version: 2.1
Name: ntsubtree
Version: 1.1
Summary: Tree representation for fast queries of the subtree of a taxon in the NCBI taxonomy tree
Home-page: https://github.com/ggonnella/fastsubtrees/tree/main/ntsubtree
Author: Giorgio Gonnella and and others (see CONTRIBUTORS)
Author-email: gonnella@zbh.uni-hamburg.de
License: ISC
Keywords: bioinformatics genomics taxonomy trees
Platform: UNKNOWN
Classifier: Development Status :: 5 - Production/Stable
Classifier: Environment :: Console
Classifier: Intended Audience :: Developers
Classifier: Intended Audience :: End Users/Desktop
Classifier: Intended Audience :: Science/Research
Classifier: License :: OSI Approved :: ISC License (ISCL)
Classifier: Operating System :: MacOS :: MacOS X
Classifier: Operating System :: POSIX :: Linux
Classifier: Programming Language :: Python :: 3 :: Only
Classifier: Topic :: Scientific/Engineering :: Bio-Informatics
Classifier: Topic :: Software Development :: Libraries
License-File: LICENSE.txt
License-File: AUTHORS.txt
Requires-Dist: tqdm (>=4.57.0)
Requires-Dist: loguru (>=0.5.1)
Requires-Dist: docopt (>=0.6.2)
Requires-Dist: schema (>=0.7.4)
Requires-Dist: sh (>=1.14.2)
Requires-Dist: ntdownload
Requires-Dist: fastsubtrees
Requires-Dist: PlatformDirs
